Workbook

Sheet InpC
F6: Constant | G6: Unit | H6: Total
A7: TIMELINE
B9: Model Start
E10: Model Start Date | F10: =J10 -> 45658 | G10: Date | J10: 45658
B12: Actuals
E13: Actual Start Date | F13: =J13 -> 45658 | G13: Date | J13: 45658
E14: Actual End Date | F14: =J14 -> 46022 | G14: Date | J14: 46022
B16: Projections
E17: Projection Start Date | F17: =J17 -> 46023 | G17: Date | J17: =J14 + 1 -> 46023
E18: Projection End Date | F18: =J18 -> 47848 | G18: Date | J18: 47848
A20: OPERATIONS
B22: Alpha Manufacturers Ltd
E23: Revenue | F23: =J23 -> 5000 | G23: INR Crs | J23: 5000
E24: Revenue Growth Rate | F24: =J24 -> 0.08 | G24: % | J24: 0.08
E25: EBITDA Margin | F25: =J25 -> 0.22 | G25: % | J25: 0.22
E26: Depreciation | F26: =J26 -> 0.03 | G26: % of Revenue | J26: 0.03
E27: Interest Rate | F27: =J27 -> 0.1 | G27: % | J27: 0.1
E28: Corporate Tax Rate | F28: =J28 -> 0.25 | G28: % | J28: 0.25
E29: Capital Expenditure | F29: =J29 -> 0.08 | G29: % of Revenue | J29: 0.08
E30: Pre- Transaction Shares Oustanding | F30: =J30 -> 100 | G30: Crores | J30: 100
C32: Balance Sheet Inputs
E33: Fixed Assets | F33: =J33 -> 2500 | G33: INR Crs | J33: 2500
E34: Working Capital | F34: =J34 -> 1300 | G34: INR Crs | J34: 1300
E35: Cash | F35: =J35 -> 400 | G35: INR Crs | J35: 400
E36: Total Assets | F36: =J36 -> 4200 | G36: INR Crs | J36: =SUM(J33:J35) -> 4200
E38: Equity (Net Worth) | F38: =J38 -> 2200 | G38: INR Crs | J38: 2200
E39: Long-term Debt | F39: =J39 -> 1000 | G39: INR Crs | J39: 1000
E40: Other Liabilities | F40: =J40 -> 1000 | G40: INR Crs | J40: 1000
E41: Total Liabilities | F41: =J41 -> 4200 | G41: INR Crs | J41: =SUM(J38:J40) -> 4200
B43: Beta Componenets Pvt. Ltd.
E44: Revenue | F44: =J44 -> 1200 | G44: INR Crs | J44: 1200
E45: Revenue Growth Rate | F45: =J45 -> 0.1 | G45: % | J45: 0.1
E46: Depreciation | F46: =J46 -> 0.05 | G46: % of Revenue | J46: 0.05
E47: Interest Rate | F47: =J47 -> 0.11 | G47: % | J47: 0.11
E48: Corporate Tax Rate | F48: =J48 -> 0.25 | G48: % | J48: 0.25
E49: Capital Expenditure | F49: =J49 -> 0.1 | G49: % of Revenue | J49: 0.1
E50: WACC | F50: =J50 -> 0.12 | G50: % | J50: 0.12
E51: Terminal Growth Rate | F51: =J51 -> 0.04 | G51: % | J51: 0.04
C53: Balance Sheet Inputs
E54: Fixed Assets | F54: =J54 -> 950 | G54: INR Crs | J54: 950
E55: Working Capital | F55: =J55 -> 480 | G55: INR Crs | J55: 480
E56: Cash | F56: =J56 -> 120 | G56: INR Crs | J56: 120
E57: Total Assets | F57: =J57 -> 1550 | G57: INR Crs | J57: =SUM(J54:J56) -> 1550
E59: Equity (Net Worth) | F59: =J59 -> 700 | G59: INR Crs | J59: 700
E60: Long-term Debt | F60: =J60 -> 400 | G60: INR Crs | J60: 400
E61: Other Liabilities | F61: =J61 -> 450 | G61: INR Crs | J61: 450
E62: Total Liabilities | F62: =J62 -> 1550 | G62: INR Crs | J62: =SUM(J59:J61) -> 1550
A64: TRANSACTION INPUTS
E66: Transaction Date | F66: =J66 -> 46023 | G66: Date | J66: 46023
E67: Transaction Premium | F67: =J67 -> 0.25 | G67: % | J67: 0.25
E68: Target Acquisition Proportion | F68: =J68 -> 1 | G68: % | J68: 1
D70: Deal Structure
E71: Cash | F71: =J71 -> 0.8 | G71: % | J71: 0.8
E72: Stock | F72: =J72 -> 0.2 | G72: % | J72: =1-J71 -> 0.2
E74: Debt Raised in Lieu of Cash | F74: =J74 -> 1 | G74: % | J74: 1
E76: Alpha Ltd. Share Price | F76: =J76 -> 65 | G76: INR | J76: 65
E78: Transaction Expenses | F78: =J78 -> 0.01 | G78: % of Transaction Value | J78: 0.01
A80: POST TRANSACTION INPUTS
B82: Synergies
E83: Cost Synergies | F83: =J83 -> 80 | G83: INR Crs | J83: 80
E84: Cost Synergies - Start Year | F84: =J84 -> 2 | G84: Year | J84: 2
E85: Integration Cost | F85: =J85 -> 100 | G85: INR Crs | J85: 100
B87: Debt
E88: Interest Rate | F88: =J88 -> 0.11 | G88: % | J88: 0.11

Sheet InpS
F6: Constant | G6: Unit | H6: Total

Sheet Alpha
E1: =E$13 -> Period Start | F1: =F$13 -> 0 | G1: =G$13 -> Date | H1: =H$13 -> 0 | I1: =I$13 -> 0 | J1: =J$13 -> 45658 | K1: =K$13 -> 46023 | L1: =L$13 -> 46388 | ... O1: =O$13 -> 47484
E2: =E$14 -> Period End | F2: =F$14 -> 0 | G2: =G$14 -> Date | H2: =H$14 -> 0 | I2: =I$14 -> 0 | J2: =J$14 -> 46022 | K2: =K$14 -> 46387 | L2: =L$14 -> 46752 | ... O2: =O$14 -> 47848
E3: =E$15 -> Number of Days | F3: =F$15 -> 0 | G3: =G$15 -> Days | H3: =H$15 -> 0 | I3: =I$15 -> 0 | J3: =J$15 -> 365 | K3: =K$15 -> 365 | L3: =L$15 -> 365 | ... O3: =O$15 -> 365
E4: =E$16 -> Financial Year | F4: =F$16 -> 0 | G4: =G$16 -> Year | H4: =H$16 -> 0 | I4: =I$16 -> 0 | J4: =J$16 -> 2025 | K4: =K$16 -> 2026 | L4: =L$16 -> 2027 | ... O4: =O$16 -> 2030
F6: Constant | G6: Unit | H6: Total
A7: TIMELINE
E9: Model Counter | G9: Counter | J9: =I9+ 1 -> 1 | K9: =J9+ 1 -> 2 | L9: =K9+ 1 -> 3 | M9: =L9+ 1 -> 4 | N9: =M9+ 1 -> 5 | O9: =N9+ 1 -> 6
E11: =InpC!E$10 -> Model Start Date | F11: =InpC!F$10 -> 45658 | G11: =InpC!G$10 -> Date
E13: Period Start | G13: Date | J13: =IF(J9 = 1, $F11, I14 + 1) -> 45658 | K13: =IF(K9 = 1, $F11, J14 + 1) -> 46023 | L13: =IF(L9 = 1, $F11, K14 + 1) -> 46388 | M13: =IF(M9 = 1, $F11, L14 + 1) -> 46753 | N13: =IF(N9 = 1, $F11, M14 + 1) -> 47119 | O13: =IF(O9 = 1, $F11, N14 + 1) -> 47484
E14: Period End | G14: Date | J14: =EOMONTH(J13, 11) -> 46022 | K14: =EOMONTH(K13, 11) -> 46387 | L14: =EOMONTH(L13, 11) -> 46752 | M14: =EOMONTH(M13, 11) -> 47118 | N14: =EOMONTH(N13, 11) -> 47483 | O14: =EOMONTH(O13, 11) -> 47848
E15: Number of Days | G15: Days | J15: =_xlfn.DAYS(J14, J13 ) + 1 -> 365 | K15: =_xlfn.DAYS(K14, K13 ) + 1 -> 365 | L15: =_xlfn.DAYS(L14, L13 ) + 1 -> 365 | M15: =_xlfn.DAYS(M14, M13 ) + 1 -> 366 | N15: =_xlfn.DAYS(N14, N13 ) + 1 -> 365 | O15: =_xlfn.DAYS(O14, O13 ) + 1 -> 365
E16: Financial Year | G16: Year | J16: =YEAR(J14) -> 2025 | K16: =YEAR(K14) -> 2026 | L16: =YEAR(L14) -> 2027 | M16: =YEAR(M14) -> 2028 | N16: =YEAR(N14) -> 2029 | O16: =YEAR(O14) -> 2030
B18: Actuals
E19: =InpC!E$13 -> Actual Start Date | F19: =InpC!F$13 -> 45658 | G19: =InpC!G$13 -> Date
E20: =InpC!E$14 -> Actual End Date | F20: =InpC!F$14 -> 46022 | G20: =InpC!G$14 -> Date
E21: Actuals Start | G21: Flag | H21: =SUM(J21:O21) -> 1 | J21: =IF(AND($F19>=J$13, $F19<=J$14), 1, 0) -> 1 | K21: =IF(AND($F19>=K$13, $F19<=K$14), 1, 0) -> 0 | L21: =IF(AND($F19>=L$13, $F19<=L$14), 1, 0) -> 0 | M21: =IF(AND($F19>=M$13, $F19<=M$14), 1, 0) -> 0 | N21: =IF(AND($F19>=N$13, $F19<=N$14), 1, 0) -> 0 | O21: =IF(AND($F19>=O$13, $F19<=O$14), 1, 0) -> 0
E22: Actuals End | G22: Flag | H22: =SUM(J22:O22) -> 1 | J22: =IF(AND($F20>=J$13, $F20<=J$14), 1, 0) -> 1 | K22: =IF(AND($F20>=K$13, $F20<=K$14), 1, 0) -> 0 | L22: =IF(AND($F20>=L$13, $F20<=L$14), 1, 0) -> 0 | M22: =IF(AND($F20>=M$13, $F20<=M$14), 1, 0) -> 0 | N22: =IF(AND($F20>=N$13, $F20<=N$14), 1, 0) -> 0 | O22: =IF(AND($F20>=O$13, $F20<=O$14), 1, 0) -> 0
E23: Actuals Active | G23: Flag | H23: =SUM(J23:O23) -> 1 | J23: =J21 +I23 - I22 -> 1 | K23: =K21 +J23 - J22 -> 0 | L23: =L21 +K23 - K22 -> 0 | M23: =M21 +L23 - L22 -> 0 | N23: =N21 +M23 - M22 -> 0 | O23: =O21 +N23 - N22 -> 0
B25: Projections
E26: =InpC!E$17 -> Projection Start Date | F26: =InpC!F$17 -> 46023 | G26: =InpC!G$17 -> Date
E27: =InpC!E$18 -> Projection End Date | F27: =InpC!F$18 -> 47848 | G27: =InpC!G$18 -> Date
E28: Projections Start | G28: Flag | H28: =SUM(J28:O28) -> 1 | J28: =IF(AND($F26>=J$13, $F26<=J$14), 1, 0) -> 0 | K28: =IF(AND($F26>=K$13, $F26<=K$14), 1, 0) -> 1 | L28: =IF(AND($F26>=L$13, $F26<=L$14), 1, 0) -> 0 | M28: =IF(AND($F26>=M$13, $F26<=M$14), 1, 0) -> 0 | N28: =IF(AND($F26>=N$13, $F26<=N$14), 1, 0) -> 0 | O28: =IF(AND($F26>=O$13, $F26<=O$14), 1, 0) -> 0
E29: Projections End | G29: Flag | H29: =SUM(J29:O29) -> 1 | J29: =IF(AND($F27>=J$13, $F27<=J$14), 1, 0) -> 0 | K29: =IF(AND($F27>=K$13, $F27<=K$14), 1, 0) -> 0 | L29: =IF(AND($F27>=L$13, $F27<=L$14), 1, 0) -> 0 | M29: =IF(AND($F27>=M$13, $F27<=M$14), 1, 0) -> 0 | N29: =IF(AND($F27>=N$13, $F27<=N$14), 1, 0) -> 0 | O29: =IF(AND($F27>=O$13, $F27<=O$14), 1, 0) -> 1
E30: Projections Active | G30: Flag | H30: =SUM(J30:O30) -> 5 | J30: =J28 +I30 - I29 -> 0 | K30: =K28 +J30 - J29 -> 1 | L30: =L28 +K30 - K29 -> 1 | M30: =M28 +L30 - L29 -> 1 | N30: =N28 +M30 - M29 -> 1 | O30: =O28 +N30 - N29 -> 1
A32: FINANCIAL STATEMENTS
B34: Income Statement
E35: =E$89 -> Revenue | F35: =F$89 -> 0 | G35: =G$89 -> INR Crs | H35: =H$89 -> 0 | I35: =I$89 -> 0 | J35: =J$89 -> 5000 | K35: =K$89 -> 5400 | L35: =L$89 -> 5832 | ... O35: =O$89 -> 7346.6404
E36: Operating Expenses | G36: INR Crs | J36: =J35 - J37 -> 3900 | K36: =K35 - K37 -> 4212 | L36: =L35 - L37 -> 4548.96 | M36: =M35 - M37 -> 4912.8768 | N36: =N35 - N37 -> 5305.9069 | O36: =O35 - O37 -> 5730.3795
E37: =E$95 -> EBITDA | F37: =F$95 -> 0 | G37: =G$95 -> INR Crs | H37: =H$95 -> 0 | I37: =I$95 -> 0 | J37: =J$95 -> 1100 | K37: =K$95 -> 1188 | L37: =L$95 -> 1283.04 | ... O37: =O$95 -> 1616.2609
E39: =E$100 -> Depreciation | F39: =F$100 -> 0 | G39: =G$100 -> INR Crs | H39: =H$100 -> 0 | I39: =I$100 -> 0 | J39: =J$100 -> 150 | K39: =K$100 -> 162 | L39: =L$100 -> 174.96 | ... O39: =O$100 -> 220.39921
E40: EBIT | G40: INR Crs | J40: =J37 - J39 -> 950 | K40: =K37 - K39 -> 1026 | L40: =L37 - L39 -> 1108.08 | M40: =M37 - M39 -> 1196.7264 | N40: =N37 - N39 -> 1292.4645 | O40: =O37 - O39 -> 1395.8617
E42: =E$114 -> Interest Expense | F42: =F$114 -> 0 | G42: =G$114 -> INR Crs | H42: =H$114 -> 0 | I42: =I$114 -> 0 | J42: =J$114 -> 0 | K42: =K$114 -> 100 | L42: =L$114 -> 100 | ... O42: =O$114 -> 100
E43: Profit Before Tax | G43: INR Crs | J43: =J40 - J42 -> 950 | K43: =K40 - K42 -> 926 | L43: =L40 - L42 -> 1008.08 | M43: =M40 - M42 -> 1096.7264 | N43: =N40 - N42 -> 1192.4645 | O43: =O40 - O42 -> 1295.8617
E45: =E$120 -> Tax Expense | F45: =F$120 -> 0 | G45: =G$120 -> INR Crs | H45: =H$120 -> 0 | I45: =I$120 -> 0 | J45: 300 | K45: =K$120 -> 231.5 | L45: =L$120 -> 252.02 | M45: =M$120 -> 274.1816 | N45: =N$120 -> 298.11613 | O45: =O$120 -> 323.96542
E46: Profit After Tax | G46: INR Crs | J46: =J43 - J45 -> 650 | K46: =K43 - K45 -> 694.5 | L46: =L43 - L45 -> 756.06 | M46: =M43 - M45 -> 822.5448 | N46: =N43 - N45 -> 894.34838 | O46: =O43 - O45 -> 971.89625
E48: Shares Outstanding | G48: Crores | J48: =InpC!$F$30 -> 100 | K48: =InpC!$F$30 -> 100 | L48: =InpC!$F$30 -> 100 | M48: =InpC!$F$30 -> 100 | N48: =InpC!$F$30 -> 100 | O48: =InpC!$F$30 -> 100
E49: Earnings Per Share | G49: INR | J49: =J46/ J48 -> 6.5 | K49: =K46/ K48 -> 6.945 | L49: =L46/ L48 -> 7.5606 | M49: =M46/ M48 -> 8.225448 | N49: =N46/ N48 -> 8.9434838 | O49: =O46/ O48 -> 9.7189625
B51: Balance Sheet
C52: Assets
E53: Fixed Assets | G53: INR Crs | J53: 2500 | K53: =K$132 -> 2770 | L53: =L$132 -> 3061.6 | M53: =M$132 -> 3376.528 | N53: =N$132 -> 3716.6502 | O53: =O$132 -> 4083.9823
E54: Working Capital | G54: INR Crs | J54: 1300 | K54: =J54 -> 1300 | L54: =K54 -> 1300 | M54: =L54 -> 1300 | N54: =M54 -> 1300 | O54: =N54 -> 1300
E55: Cash | G55: INR Crs | J55: 400 | K55: =K$80 -> 824.5 | L55: =L$80 -> 1288.96 | M55: =M$80 -> 1796.5768 | N55: =N$80 -> 2350.8029 | O55: =O$80 -> 2955.3672
E56: Total Assets | G56: INR Crs | J56: =SUM(J53:J55) -> 4200 | K56: =SUM(K53:K55) -> 4894.5 | L56: =SUM(L53:L55) -> 5650.56 | M56: =SUM(M53:M55) -> 6473.1048 | N56: =SUM(N53:N55) -> 7367.4532 | O56: =SUM(O53:O55) -> 8339.3494
C58: Liabilities
E59: Equity (Net Worth) | G59: INR Crs | J59: 2200 | K59: =K$144 -> 2894.5 | L59: =L$144 -> 3650.56 | M59: =M$144 -> 4473.1048 | N59: =N$144 -> 5367.4532 | O59: =O$144 -> 6339.3494
E60: Long-term Debt | G60: INR Crs | J60: 1000 | K60: =K$111 -> 1000 | L60: =L$111 -> 1000 | M60: =M$111 -> 1000 | N60: =N$111 -> 1000 | O60: =O$111 -> 1000
E61: Other Liabilities | G61: INR Crs | J61: 1000 | K61: =J61 -> 1000 | L61: =K61 -> 1000 | M61: =L61 -> 1000 | N61: =M61 -> 1000 | O61: =N61 -> 1000
E62: Total Liabilities | G62: INR Crs | J62: =SUM(J59:J61) -> 4200 | K62: =SUM(K59:K61) -> 4894.5 | L62: =SUM(L59:L61) -> 5650.56 | M62: =SUM(M59:M61) -> 6473.1048 | N62: =SUM(N59:N61) -> 7367.4532 | O62: =SUM(O59:O61) -> 8339.3494
E64: Balance sheet - Check | J64: =ROUND(J56 - J62, 0) -> 0 | K64: =ROUND(K56 - K62, 0) -> 0 | L64: =ROUND(L56 - L62, 0) -> 0 | M64: =ROUND(M56 - M62, 0) -> 0 | N64: =ROUND(N56 - N62, 0) -> 0 | O64: =ROUND(O56 - O62, 0) -> 0
B66: Cash Flow Statement
E67: =E$46 -> Profit After Tax | F67: =F$46 -> 0 | G67: =G$46 -> INR Crs | H67: =H$46 -> 0 | I67: =I$46 -> 0 | J67: =J$46 * J$30 -> 0 | K67: =K$46 * K$30 -> 694.5 | L67: =L$46 * L$30 -> 756.06 | M67: =M$46 * M$30 -> 822.5448 | N67: =N$46 * N$30 -> 894.34838 | O67: =O$46 * O$30 -> 971.89625
E68: =E$39 -> Depreciation | F68: =F$39 -> 0 | G68: =G$39 -> INR Crs | H68: =H$39 -> 0 | I68: =I$39 -> 0 | J68: =J$39 * J$30 -> 0 | K68: =K$39 * K$30 -> 162 | L68: =L$39 * L$30 -> 174.96 | M68: =M$39 * M$30 -> 188.9568 | N68: =N$39 * N$30 -> 204.07334 | O68: =O$39 * O$30 -> 220.39921
E69: Changes in working capital | G69: INR Crs | J69: =(I54 - J54)* J$30 -> 0 | K69: =(J54 - K54)* K$30 -> 0 | L69: =(K54 - L54)* L$30 -> 0 | M69: =(L54 - M54)* M$30 -> 0 | N69: =(M54 - N54)* N$30 -> 0 | O69: =(N54 - O54)* O$30 -> 0
E70: Cash Flow From Operations | G70: INR Crs | J70: =SUM(J67:J69) -> 0 | K70: =SUM(K67:K69) -> 856.5 | L70: =SUM(L67:L69) -> 931.02 | M70: =SUM(M67:M69) -> 1011.5016 | N70: =SUM(N67:N69) -> 1098.4217 | O70: =SUM(O67:O69) -> 1192.2955
E72: Capital Expenditure | G72: INR Crs | J72: =-1* J$130 -> 0 | K72: =-1* K$130 -> -432 | L72: =-1* L$130 -> -466.56 | M72: =-1* M$130 -> -503.8848 | N72: =-1* N$130 -> -544.19558 | O72: =-1* O$130 -> -587.73123
E73: Cash Flow From Investing Activities | G73: INR Crs | J73: =SUM(J72) -> 0 | K73: =SUM(K72) -> -432 | L73: =SUM(L72) -> -466.56 | M73: =SUM(M72) -> -503.8848 | N73: =SUM(N72) -> -544.19558 | O73: =SUM(O72) -> -587.73123
E76: Cash Flow From Financing Activities | G76: INR Crs | J76: =SUM(J75) -> 0 | K76: =SUM(K75) -> 0 | L76: =SUM(L75) -> 0 | M76: =SUM(M75) -> 0 | N76: =SUM(N75) -> 0 | O76: =SUM(O75) -> 0
E78: Opening Cash | G78: INR Crs | K78: =J80 -> 400 | L78: =K80 -> 824.5 | M78: =L80 -> 1288.96 | N78: =M80 -> 1796.5768 | O78: =N80 -> 2350.8029
E79: Net Change in Cash | G79: INR Crs | K79: =K70 +K73 + K76 -> 424.5 | L79: =L70 +L73 + L76 -> 464.46 | M79: =M70 +M73 + M76 -> 507.6168 | N79: =N70 +N73 + N76 -> 554.22614 | O79: =O70 +O73 + O76 -> 604.56424
E80: Closing Cash | G80: INR Crs | J80: =J55 -> 400 | K80: =SUM(K78:K79) -> 824.5 | L80: =SUM(L78:L79) -> 1288.96 | M80: =SUM(M78:M79) -> 1796.5768 | N80: =SUM(N78:N79) -> 2350.8029 | O80: =SUM(O78:O79) -> 2955.3672
A82: WORKINGS
C84: Revenue
E85: =InpC!E$23 -> Revenue | F85: =InpC!F$23 -> 5000 | G85: =InpC!G$23 -> INR Crs
E86: =InpC!E$24 -> Revenue Growth Rate | F86: =InpC!F$24 -> 0.08 | G86: =InpC!G$24 -> %
E87: =E$23 -> Actuals Active | F87: =F$23 -> 0 | G87: =G$23 -> Flag | H87: =H$23 -> 1 | I87: =I$23 -> 0 | J87: =J$23 -> 1 | K87: =K$23 -> 0 | L87: =L$23 -> 0 | ... O87: =O$23 -> 0
E88: =E$30 -> Projections Active | F88: =F$30 -> 0 | G88: =G$30 -> Flag | H88: =H$30 -> 5 | I88: =I$30 -> 0 | J88: =J$30 -> 0 | K88: =K$30 -> 1 | L88: =L$30 -> 1 | ... O88: =O$30 -> 1
E89: Revenue | G89: INR Crs | J89: =IF(J87=1,$F85,IF(J88=1,I89*(1+J90),0)) -> 5000 | K89: =IF(K87=1,$F85,IF(K88=1,J89*(1+K90),0)) -> 5400 | L89: =IF(L87=1,$F85,IF(L88=1,K89*(1+L90),0)) -> 5832 | M89: =IF(M87=1,$F85,IF(M88=1,L89*(1+M90),0)) -> 6298.56 | N89: =IF(N87=1,$F85,IF(N88=1,M89*(1+N90),0)) -> 6802.4448 | O89: =IF(O87=1,$F85,IF(O88=1,N89*(1+O90),0)) -> 7346.6404
E90: Revenue Growth Rate | G90: % | J90: =IF(J88=1, $F86, 0) -> 0 | K90: =IF(K88=1, $F86, 0) -> 0.08 | L90: =IF(L88=1, $F86, 0) -> 0.08 | M90: =IF(M88=1, $F86, 0) -> 0.08 | N90: =IF(N88=1, $F86, 0) -> 0.08 | O90: =IF(O88=1, $F86, 0) -> 0.08
C92: EBITDA
E93: =InpC!E$25 -> EBITDA Margin | F93: =InpC!F$25 -> 0.22 | G93: =InpC!G$25 -> %
E94: =E$89 -> Revenue | F94: =F$89 -> 0 | G94: =G$89 -> INR Crs | H94: =H$89 -> 0 | I94: =I$89 -> 0 | J94: =J$89 -> 5000 | K94: =K$89 -> 5400 | L94: =L$89 -> 5832 | ... O94: =O$89 -> 7346.6404
E95: EBITDA | G95: INR Crs | J95: =$F93 * J94 -> 1100 | K95: =$F93 * K94 -> 1188 | L95: =$F93 * L94 -> 1283.04 | M95: =$F93 * M94 -> 1385.6832 | N95: =$F93 * N94 -> 1496.5379 | O95: =$F93 * O94 -> 1616.2609
C97: Depreciation
E98: =InpC!E$26 -> Depreciation | F98: =InpC!F$26 -> 0.03 | G98: =InpC!G$26 -> % of Revenue
E99: =E$89 -> Revenue | F99: =F$89 -> 0 | G99: =G$89 -> INR Crs | H99: =H$89 -> 0 | I99: =I$89 -> 0 | J99: =J$89 -> 5000 | K99: =K$89 -> 5400 | L99: =L$89 -> 5832 | ... O99: =O$89 -> 7346.6404
E100: Depreciation | G100: INR Crs | J100: =$F98 * J99 -> 150 | K100: =$F98 * K99 -> 162 | L100: =$F98 * L99 -> 174.96 | M100: =$F98 * M99 -> 188.9568 | N100: =$F98 * N99 -> 204.07334 | O100: =$F98 * O99 -> 220.39921
C103: Long Term Debt
E104: =InpC!E$27 -> Interest Rate | F104: =InpC!F$27 -> 0.1 | G104: =InpC!G$27 -> %
E105: =InpC!E$39 -> Long-term Debt | F105: =InpC!F$39 -> 1000 | G105: =InpC!G$39 -> INR Crs
E107: =E$28 -> Projections Start | F107: =F$28 -> 0 | G107: =G$28 -> Flag | H107: =H$28 -> 1 | I107: =I$28 -> 0 | J107: =J$28 -> 0 | K107: =K$28 -> 1 | L107: =L$28 -> 0 | ... O107: =O$28 -> 0
E108: Long Term Debt - Opening Balance | G108: INR Crs | J108: =IF(J107=1, $F105, I111) -> 0 | K108: =IF(K107=1, $F105, J111) -> 1000 | L108: =IF(L107=1, $F105, K111) -> 1000 | M108: =IF(M107=1, $F105, L111) -> 1000 | N108: =IF(N107=1, $F105, M111) -> 1000 | O108: =IF(O107=1, $F105, N111) -> 1000
E109: Long Term Debt - Addition | G109: INR Crs
E110: Long Term Debt - Repayment | G110: INR Crs
E111: Long Term Debt - Closing Balance | G111: INR Crs | J111: =J108 + J109 - J110 -> 0 | K111: =K108 + K109 - K110 -> 1000 | L111: =L108 + L109 - L110 -> 1000 | M111: =M108 + M109 - M110 -> 1000 | N111: =N108 + N109 - N110 -> 1000 | O111: =O108 + O109 - O110 -> 1000
E113: =E$30 -> Projections Active | F113: =F$30 -> 0 | G113: =G$30 -> Flag | H113: =H$30 -> 5 | I113: =I$30 -> 0 | J113: =J$30 -> 0 | K113: =K$30 -> 1 | L113: =L$30 -> 1 | ... O113: =O$30 -> 1
E114: Interest Expense | G114: INR Crs | J114: =IF(J113=1,$F104*SUM(J108:J109), 0) -> 0 | K114: =IF(K113=1,$F104*SUM(K108:K109), 0) -> 100 | L114: =IF(L113=1,$F104*SUM(L108:L109), 0) -> 100 | M114: =IF(M113=1,$F104*SUM(M108:M109), 0) -> 100 | N114: =IF(N113=1,$F104*SUM(N108:N109), 0) -> 100 | O114: =IF(O113=1,$F104*SUM(O108:O109), 0) -> 100
C116: Corporate Income Tax Rate
E117: =InpC!E$28 -> Corporate Tax Rate | F117: =InpC!F$28 -> 0.25 | G117: =InpC!G$28 -> %
E118: =E$30 -> Projections Active | F118: =F$30 -> 0 | G118: =G$30 -> Flag | H118: =H$30 -> 5 | I118: =I$30 -> 0 | J118: =J$30 -> 0 | K118: =K$30 -> 1 | L118: =L$30 -> 1 | ... O118: =O$30 -> 1
E119: =E$43 -> Profit Before Tax | F119: =F$43 -> 0 | G119: =G$43 -> INR Crs | H119: =H$43 -> 0 | I119: =I$43 -> 0 | J119: =J$43 -> 950 | K119: =K$43 -> 926 | L119: =L$43 -> 1008.08 | ... O119: =O$43 -> 1295.8617
E120: Tax Expense | G120: INR Crs | J120: =IF(J118=1, $F117 * J$119, 0) -> 0 | K120: =IF(K118=1, $F117 * K$119, 0) -> 231.5 | L120: =IF(L118=1, $F117 * L$119, 0) -> 252.02 | M120: =IF(M118=1, $F117 * M$119, 0) -> 274.1816 | N120: =IF(N118=1, $F117 * N$119, 0) -> 298.11613 | O120: =IF(O118=1, $F117 * O$119, 0) -> 323.96542
C122: Fixed Assets
E123: =InpC!E$29 -> Capital Expenditure | F123: =InpC!F$29 -> 0.08 | G123: =InpC!G$29 -> % of Revenue
E124: =InpC!E$33 -> Fixed Assets | F124: =InpC!F$33 -> 2500 | G124: =InpC!G$33 -> INR Crs
E125: =E$30 -> Projections Active | F125: =F$30 -> 0 | G125: =G$30 -> Flag | H125: =H$30 -> 5 | I125: =I$30 -> 0 | J125: =J$30 -> 0 | K125: =K$30 -> 1 | L125: =L$30 -> 1 | ... O125: =O$30 -> 1
E126: =E$89 -> Revenue | F126: =F$89 -> 0 | G126: =G$89 -> INR Crs | H126: =H$89 -> 0 | I126: =I$89 -> 0 | J126: =J$89 -> 5000 | K126: =K$89 -> 5400 | L126: =L$89 -> 5832 | ... O126: =O$89 -> 7346.6404
E128: =E$28 -> Projections Start | F128: =F$28 -> 0 | G128: =G$28 -> Flag | H128: =H$28 -> 1 | I128: =I$28 -> 0 | J128: =J$28 -> 0 | K128: =K$28 -> 1 | L128: =L$28 -> 0 | ... O128: =O$28 -> 0
E129: Fixed Assets - Opening Balance | G129: INR Crs | J129: =IF(J128=1, $F124, I132) -> 0 | K129: =IF(K128=1, $F124, J132) -> 2500 | L129: =IF(L128=1, $F124, K132) -> 2770 | M129: =IF(M128=1, $F124, L132) -> 3061.6 | N129: =IF(N128=1, $F124, M132) -> 3376.528 | O129: =IF(O128=1, $F124, N132) -> 3716.6502
E130: Fixed Assets - Capital Expenditure | G130: INR Crs | J130: =IF(J125=1, $F123 * J$126, 0) -> 0 | K130: =IF(K125=1, $F123 * K$126, 0) -> 432 | L130: =IF(L125=1, $F123 * L$126, 0) -> 466.56 | M130: =IF(M125=1, $F123 * M$126, 0) -> 503.8848 | N130: =IF(N125=1, $F123 * N$126, 0) -> 544.19558 | O130: =IF(O125=1, $F123 * O$126, 0) -> 587.73123
E131: Fixed Assets - Depreciation | G131: INR Crs | K131: =K$100 -> 162 | L131: =L$100 -> 174.96 | M131: =M$100 -> 188.9568 | N131: =N$100 -> 204.07334 | O131: =O$100 -> 220.39921
...

Sheet Beta
E1: =E$13 -> Period Start | F1: =F$13 -> 0 | G1: =G$13 -> Date | H1: =H$13 -> 0 | I1: =I$13 -> 0 | J1: =J$13 -> 45658 | K1: =K$13 -> 46023 | L1: =L$13 -> 46388 | ... O1: =O$13 -> 47484
E2: =E$14 -> Period End | F2: =F$14 -> 0 | G2: =G$14 -> Date | H2: =H$14 -> 0 | I2: =I$14 -> 0 | J2: =J$14 -> 46022 | K2: =K$14 -> 46387 | L2: =L$14 -> 46752 | ... O2: =O$14 -> 47848
E3: =E$15 -> Number of Days | F3: =F$15 -> 0 | G3: =G$15 -> Days | H3: =H$15 -> 0 | I3: =I$15 -> 0 | J3: =J$15 -> 365 | K3: =K$15 -> 365 | L3: =L$15 -> 365 | ... O3: =O$15 -> 365
E4: =E$16 -> Financial Year | F4: =F$16 -> 0 | G4: =G$16 -> Year | H4: =H$16 -> 0 | I4: =I$16 -> 0 | J4: =J$16 -> 2025 | K4: =K$16 -> 2026 | L4: =L$16 -> 2027 | ... O4: =O$16 -> 2030
F6: Constant | G6: Unit | H6: Total
A7: TIMELINE
E9: Model Counter | G9: Counter | J9: =I9+ 1 -> 1 | K9: =J9+ 1 -> 2 | L9: =K9+ 1 -> 3 | M9: =L9+ 1 -> 4 | N9: =M9+ 1 -> 5 | O9: =N9+ 1 -> 6
E11: =InpC!E$10 -> Model Start Date | F11: =InpC!F$10 -> 45658 | G11: =InpC!G$10 -> Date
E13: Period Start | G13: Date | J13: =IF(J9 = 1, $F11, I14 + 1) -> 45658 | K13: =IF(K9 = 1, $F11, J14 + 1) -> 46023 | L13: =IF(L9 = 1, $F11, K14 + 1) -> 46388 | M13: =IF(M9 = 1, $F11, L14 + 1) -> 46753 | N13: =IF(N9 = 1, $F11, M14 + 1) -> 47119 | O13: =IF(O9 = 1, $F11, N14 + 1) -> 47484
E14: Period End | G14: Date | J14: =EOMONTH(J13, 11) -> 46022 | K14: =EOMONTH(K13, 11) -> 46387 | L14: =EOMONTH(L13, 11) -> 46752 | M14: =EOMONTH(M13, 11) -> 47118 | N14: =EOMONTH(N13, 11) -> 47483 | O14: =EOMONTH(O13, 11) -> 47848
E15: Number of Days | G15: Days | J15: =_xlfn.DAYS(J14, J13 ) + 1 -> 365 | K15: =_xlfn.DAYS(K14, K13 ) + 1 -> 365 | L15: =_xlfn.DAYS(L14, L13 ) + 1 -> 365 | M15: =_xlfn.DAYS(M14, M13 ) + 1 -> 366 | N15: =_xlfn.DAYS(N14, N13 ) + 1 -> 365 | O15: =_xlfn.DAYS(O14, O13 ) + 1 -> 365
E16: Financial Year | G16: Year | J16: =YEAR(J14) -> 2025 | K16: =YEAR(K14) -> 2026 | L16: =YEAR(L14) -> 2027 | M16: =YEAR(M14) -> 2028 | N16: =YEAR(N14) -> 2029 | O16: =YEAR(O14) -> 2030
B18: Actuals
E19: =InpC!E$13 -> Actual Start Date | F19: =InpC!F$13 -> 45658 | G19: =InpC!G$13 -> Date
E20: =InpC!E$14 -> Actual End Date | F20: =InpC!F$14 -> 46022 | G20: =InpC!G$14 -> Date
E21: Actuals Start | G21: Flag | H21: =SUM(J21:O21) -> 1 | J21: =IF(AND($F19>=J$13, $F19<=J$14), 1, 0) -> 1 | K21: =IF(AND($F19>=K$13, $F19<=K$14), 1, 0) -> 0 | L21: =IF(AND($F19>=L$13, $F19<=L$14), 1, 0) -> 0 | M21: =IF(AND($F19>=M$13, $F19<=M$14), 1, 0) -> 0 | N21: =IF(AND($F19>=N$13, $F19<=N$14), 1, 0) -> 0 | O21: =IF(AND($F19>=O$13, $F19<=O$14), 1, 0) -> 0
E22: Actuals End | G22: Flag | H22: =SUM(J22:O22) -> 1 | J22: =IF(AND($F20>=J$13, $F20<=J$14), 1, 0) -> 1 | K22: =IF(AND($F20>=K$13, $F20<=K$14), 1, 0) -> 0 | L22: =IF(AND($F20>=L$13, $F20<=L$14), 1, 0) -> 0 | M22: =IF(AND($F20>=M$13, $F20<=M$14), 1, 0) -> 0 | N22: =IF(AND($F20>=N$13, $F20<=N$14), 1, 0) -> 0 | O22: =IF(AND($F20>=O$13, $F20<=O$14), 1, 0) -> 0
E23: Actuals Active | G23: Flag | H23: =SUM(J23:O23) -> 1 | J23: =J21 +I23 - I22 -> 1 | K23: =K21 +J23 - J22 -> 0 | L23: =L21 +K23 - K22 -> 0 | M23: =M21 +L23 - L22 -> 0 | N23: =N21 +M23 - M22 -> 0 | O23: =O21 +N23 - N22 -> 0
B25: Projections
E26: =InpC!E$17 -> Projection Start Date | F26: =InpC!F$17 -> 46023 | G26: =InpC!G$17 -> Date
E27: =InpC!E$18 -> Projection End Date | F27: =InpC!F$18 -> 47848 | G27: =InpC!G$18 -> Date
E28: Projections Start | G28: Flag | H28: =SUM(J28:O28) -> 1 | J28: =IF(AND($F26>=J$13, $F26<=J$14), 1, 0) -> 0 | K28: =IF(AND($F26>=K$13, $F26<=K$14), 1, 0) -> 1 | L28: =IF(AND($F26>=L$13, $F26<=L$14), 1, 0) -> 0 | M28: =IF(AND($F26>=M$13, $F26<=M$14), 1, 0) -> 0 | N28: =IF(AND($F26>=N$13, $F26<=N$14), 1, 0) -> 0 | O28: =IF(AND($F26>=O$13, $F26<=O$14), 1, 0) -> 0
E29: Projections End | G29: Flag | H29: =SUM(J29:O29) -> 1 | J29: =IF(AND($F27>=J$13, $F27<=J$14), 1, 0) -> 0 | K29: =IF(AND($F27>=K$13, $F27<=K$14), 1, 0) -> 0 | L29: =IF(AND($F27>=L$13, $F27<=L$14), 1, 0) -> 0 | M29: =IF(AND($F27>=M$13, $F27<=M$14), 1, 0) -> 0 | N29: =IF(AND($F27>=N$13, $F27<=N$14), 1, 0) -> 0 | O29: =IF(AND($F27>=O$13, $F27<=O$14), 1, 0) -> 1
E30: Projections Active | G30: Flag | H30: =SUM(J30:O30) -> 5 | J30: =J28 +I30 - I29 -> 0 | K30: =K28 +J30 - J29 -> 1 | L30: =L28 +K30 - K29 -> 1 | M30: =M28 +L30 - L29 -> 1 | N30: =N28 +M30 - M29 -> 1 | O30: =O28 +N30 - N29 -> 1
E31: Projections Period | G31: Year | J31: =I31 + J30 -> 0 | K31: =J31 + K30 -> 1 | L31: =K31 + L30 -> 2 | M31: =L31 + M30 -> 3 | N31: =M31 + N30 -> 4 | O31: =N31 + O30 -> 5
A33: FINANCIAL STATEMENTS
B35: Income Statement
E36: =E$87 -> Revenue | F36: =F$87 -> 0 | G36: =G$87 -> INR Crs | H36: =H$87 -> 0 | I36: =I$87 -> 0 | J36: =J$87 -> 1200 | K36: =K$87 -> 1320 | L36: =L$87 -> 1452 | ... O36: =O$87 -> 1932.612
E37: Operating Expenses | G37: INR Crs | J37: =J36 - J38 -> 864 | K37: =K36 - K38 -> 937.2 | L37: =L36 - L38 -> 1016.4 | M37: =M36 - M38 -> 1118.04 | N37: =N36 - N38 -> 1229.844 | O37: =O36 - O38 -> 1352.8284
E38: =E$93 -> EBITDA | F38: =F$93 -> 0 | G38: =G$93 -> INR Crs | H38: =H$93 -> 0 | I38: =I$93 -> 0 | J38: =J$93 -> 336 | K38: =K$93 -> 382.8 | L38: =L$93 -> 435.6 | ... O38: =O$93 -> 579.7836
E40: =E$98 -> Depreciation | F40: =F$98 -> 0 | G40: =G$98 -> INR Crs | H40: =H$98 -> 0 | I40: =I$98 -> 0 | J40: =J$98 -> 60 | K40: =K$98 -> 66 | L40: =L$98 -> 72.6 | ... O40: =O$98 -> 96.6306
E41: EBIT | G41: INR Crs | J41: =J38 - J40 -> 276 | K41: =K38 - K40 -> 316.8 | L41: =L38 - L40 -> 363 | M41: =M38 - M40 -> 399.3 | N41: =N38 - N40 -> 439.23 | O41: =O38 - O40 -> 483.153
E43: =E$111 -> Interest Expense | F43: =F$111 -> 0 | G43: =G$111 -> INR Crs | H43: =H$111 -> 0 | I43: =I$111 -> 0 | J43: =J$111 -> 0 | K43: =K$111 -> 44 | L43: =L$111 -> 44 | ... O43: =O$111 -> 44
E44: Profit Before Tax | G44: INR Crs | J44: =J41 - J43 -> 276 | K44: =K41 - K43 -> 272.8 | L44: =L41 - L43 -> 319 | M44: =M41 - M43 -> 355.3 | N44: =N41 - N43 -> 395.23 | O44: =O41 - O43 -> 439.153
E46: =E$117 -> Tax Expense | F46: =F$117 -> 0 | G46: =G$117 -> INR Crs | H46: =H$117 -> 0 | I46: =I$117 -> 0 | J46: 96 | K46: =K$117 -> 68.2 | L46: =L$117 -> 79.75 | M46: =M$117 -> 88.825 | N46: =N$117 -> 98.8075 | O46: =O$117 -> 109.78825
E47: Profit After Tax | G47: INR Crs | J47: =J44 - J46 -> 180 | K47: =K44 - K46 -> 204.6 | L47: =L44 - L46 -> 239.25 | M47: =M44 - M46 -> 266.475 | N47: =N44 - N46 -> 296.4225 | O47: =O44 - O46 -> 329.36475
B49: Balance Sheet
C50: Assets
E51: Fixed Assets | G51: INR Crs | J51: 950 | K51: =K$129 -> 1016 | L51: =L$129 -> 1088.6 | M51: =M$129 -> 1168.46 | N51: =N$129 -> 1256.306 | O51: =O$129 -> 1352.9366
E52: Working Capital | G52: INR Crs | J52: 480 | K52: =J52 -> 480 | L52: =K52 -> 480 | M52: =L52 -> 480 | N52: =M52 -> 480 | O52: =N52 -> 480
E53: Cash | G53: INR Crs | J53: 120 | K53: =K$78 -> 258.6 | L53: =L$78 -> 425.25 | M53: =M$78 -> 611.865 | N53: =N$78 -> 820.4415 | O53: =O$78 -> 1053.1757
E54: Total Assets | G54: INR Crs | J54: =SUM(J51:J53) -> 1550 | K54: =SUM(K51:K53) -> 1754.6 | L54: =SUM(L51:L53) -> 1993.85 | M54: =SUM(M51:M53) -> 2260.325 | N54: =SUM(N51:N53) -> 2556.7475 | O54: =SUM(O51:O53) -> 2886.1123
C56: Liabilities
E57: Equity (Net Worth) | G57: INR Crs | J57: 700 | K57: =K$141 -> 904.6 | L57: =L$141 -> 1143.85 | M57: =M$141 -> 1410.325 | N57: =N$141 -> 1706.7475 | O57: =O$141 -> 2036.1123
E58: Long-term Debt | G58: INR Crs | J58: 400 | K58: =K$108 -> 400 | L58: =L$108 -> 400 | M58: =M$108 -> 400 | N58: =N$108 -> 400 | O58: =O$108 -> 400
E59: Other Liabilities | G59: INR Crs | J59: 450 | K59: =J59 -> 450 | L59: =K59 -> 450 | M59: =L59 -> 450 | N59: =M59 -> 450 | O59: =N59 -> 450
E60: Total Liabilities | G60: INR Crs | J60: =SUM(J57:J59) -> 1550 | K60: =SUM(K57:K59) -> 1754.6 | L60: =SUM(L57:L59) -> 1993.85 | M60: =SUM(M57:M59) -> 2260.325 | N60: =SUM(N57:N59) -> 2556.7475 | O60: =SUM(O57:O59) -> 2886.1123
E62: Balance sheet - Check | J62: =ROUND(J54 - J60, 0) -> 0 | K62: =ROUND(K54 - K60, 0) -> 0 | L62: =ROUND(L54 - L60, 0) -> 0 | M62: =ROUND(M54 - M60, 0) -> 0 | N62: =ROUND(N54 - N60, 0) -> 0 | O62: =ROUND(O54 - O60, 0) -> 0
B64: Cash Flow Statement
E65: =E$47 -> Profit After Tax | F65: =F$47 -> 0 | G65: =G$47 -> INR Crs | H65: =H$47 -> 0 | I65: =I$47 -> 0 | J65: =J$47 * J$30 -> 0 | K65: =K$47 * K$30 -> 204.6 | L65: =L$47 * L$30 -> 239.25 | M65: =M$47 * M$30 -> 266.475 | N65: =N$47 * N$30 -> 296.4225 | O65: =O$47 * O$30 -> 329.36475
E66: =E$40 -> Depreciation | F66: =F$40 -> 0 | G66: =G$40 -> INR Crs | H66: =H$40 -> 0 | I66: =I$40 -> 0 | J66: =J$40 * J$30 -> 0 | K66: =K$40 * K$30 -> 66 | L66: =L$40 * L$30 -> 72.6 | M66: =M$40 * M$30 -> 79.86 | N66: =N$40 * N$30 -> 87.846 | O66: =O$40 * O$30 -> 96.6306
E67: Changes in working capital | G67: INR Crs | J67: =(I52 - J52)* J$30 -> 0 | K67: =(J52 - K52)* K$30 -> 0 | L67: =(K52 - L52)* L$30 -> 0 | M67: =(L52 - M52)* M$30 -> 0 | N67: =(M52 - N52)* N$30 -> 0 | O67: =(N52 - O52)* O$30 -> 0
E68: Cash Flow From Operations | G68: INR Crs | J68: =SUM(J65:J67) -> 0 | K68: =SUM(K65:K67) -> 270.6 | L68: =SUM(L65:L67) -> 311.85 | M68: =SUM(M65:M67) -> 346.335 | N68: =SUM(N65:N67) -> 384.2685 | O68: =SUM(O65:O67) -> 425.99535
E70: Capital Expenditure | G70: INR Crs | J70: =-1* J$127 -> 0 | K70: =-1* K$127 -> -132 | L70: =-1* L$127 -> -145.2 | M70: =-1* M$127 -> -159.72 | N70: =-1* N$127 -> -175.692 | O70: =-1* O$127 -> -193.2612
E71: Cash Flow From Investing Activities | G71: INR Crs | J71: =SUM(J70) -> 0 | K71: =SUM(K70) -> -132 | L71: =SUM(L70) -> -145.2 | M71: =SUM(M70) -> -159.72 | N71: =SUM(N70) -> -175.692 | O71: =SUM(O70) -> -193.2612
E74: Cash Flow From Financing Activities | G74: INR Crs | J74: =SUM(J73) -> 0 | K74: =SUM(K73) -> 0 | L74: =SUM(L73) -> 0 | M74: =SUM(M73) -> 0 | N74: =SUM(N73) -> 0 | O74: =SUM(O73) -> 0
E76: Opening Cash | G76: INR Crs | K76: =J78 -> 120 | L76: =K78 -> 258.6 | M76: =L78 -> 425.25 | N76: =M78 -> 611.865 | O76: =N78 -> 820.4415
E77: Net Change in Cash | G77: INR Crs | K77: =K68 +K71 + K74 -> 138.6 | L77: =L68 +L71 + L74 -> 166.65 | M77: =M68 +M71 + M74 -> 186.615 | N77: =N68 +N71 + N74 -> 208.5765 | O77: =O68 +O71 + O74 -> 232.73415
E78: Closing Cash | G78: INR Crs | J78: =J53 -> 120 | K78: =SUM(K76:K77) -> 258.6 | L78: =SUM(L76:L77) -> 425.25 | M78: =SUM(M76:M77) -> 611.865 | N78: =SUM(N76:N77) -> 820.4415 | O78: =SUM(O76:O77) -> 1053.1757
A80: WORKINGS
C82: Revenue
E83: =InpC!E$44 -> Revenue | F83: =InpC!F$44 -> 1200 | G83: =InpC!G$44 -> INR Crs
E84: =InpC!E$45 -> Revenue Growth Rate | F84: =InpC!F$45 -> 0.1 | G84: =InpC!G$45 -> %
E85: =E$23 -> Actuals Active | F85: =F$23 -> 0 | G85: =G$23 -> Flag | H85: =H$23 -> 1 | I85: =I$23 -> 0 | J85: =J$23 -> 1 | K85: =K$23 -> 0 | L85: =L$23 -> 0 | ... O85: =O$23 -> 0
E86: =E$30 -> Projections Active | F86: =F$30 -> 0 | G86: =G$30 -> Flag | H86: =H$30 -> 5 | I86: =I$30 -> 0 | J86: =J$30 -> 0 | K86: =K$30 -> 1 | L86: =L$30 -> 1 | ... O86: =O$30 -> 1
E87: Revenue | G87: INR Crs | J87: =IF(J85=1,$F83,IF(J86=1,I87*(1+J88),0)) -> 1200 | K87: =IF(K85=1,$F83,IF(K86=1,J87*(1+K88),0)) -> 1320 | L87: =IF(L85=1,$F83,IF(L86=1,K87*(1+L88),0)) -> 1452 | M87: =IF(M85=1,$F83,IF(M86=1,L87*(1+M88),0)) -> 1597.2 | N87: =IF(N85=1,$F83,IF(N86=1,M87*(1+N88),0)) -> 1756.92 | O87: =IF(O85=1,$F83,IF(O86=1,N87*(1+O88),0)) -> 1932.612
E88: Revenue Growth Rate | G88: % | J88: =IF(J86=1, $F84, 0) -> 0 | K88: =IF(K86=1, $F84, 0) -> 0.1 | L88: =IF(L86=1, $F84, 0) -> 0.1 | M88: =IF(M86=1, $F84, 0) -> 0.1 | N88: =IF(N86=1, $F84, 0) -> 0.1 | O88: =IF(O86=1, $F84, 0) -> 0.1
C90: EBITDA
E91: =E$87 -> Revenue | F91: =F$87 -> 0 | G91: =G$87 -> INR Crs | H91: =H$87 -> 0 | I91: =I$87 -> 0 | J91: =J$87 -> 1200 | K91: =K$87 -> 1320 | L91: =L$87 -> 1452 | ... O91: =O$87 -> 1932.612
E92: EBITDA Margin | G92: % | J92: 0.28 | K92: 0.29 | L92: 0.3 | M92: 0.3 | N92: 0.3 | O92: 0.3
E93: EBITDA | G93: INR Crs | J93: =J91 * J92 -> 336 | K93: =K91 * K92 -> 382.8 | L93: =L91 * L92 -> 435.6 | M93: =M91 * M92 -> 479.16 | N93: =N91 * N92 -> 527.076 | O93: =O91 * O92 -> 579.7836
C95: Depreciation
E96: =InpC!E$46 -> Depreciation | F96: =InpC!F$46 -> 0.05 | G96: =InpC!G$46 -> % of Revenue
E97: =E$87 -> Revenue | F97: =F$87 -> 0 | G97: =G$87 -> INR Crs | H97: =H$87 -> 0 | I97: =I$87 -> 0 | J97: =J$87 -> 1200 | K97: =K$87 -> 1320 | L97: =L$87 -> 1452 | ... O97: =O$87 -> 1932.612
E98: Depreciation | G98: INR Crs | J98: =$F96 * J97 -> 60 | K98: =$F96 * K97 -> 66 | L98: =$F96 * L97 -> 72.6 | M98: =$F96 * M97 -> 79.86 | N98: =$F96 * N97 -> 87.846 | O98: =$F96 * O97 -> 96.6306
C100: Long Term Debt
E101: =InpC!E$47 -> Interest Rate | F101: =InpC!F$47 -> 0.11 | G101: =InpC!G$47 -> %
E102: =InpC!E$60 -> Long-term Debt | F102: =InpC!F$60 -> 400 | G102: =InpC!G$60 -> INR Crs
E104: =E$28 -> Projections Start | F104: =F$28 -> 0 | G104: =G$28 -> Flag | H104: =H$28 -> 1 | I104: =I$28 -> 0 | J104: =J$28 -> 0 | K104: =K$28 -> 1 | L104: =L$28 -> 0 | ... O104: =O$28 -> 0
E105: Long Term Debt - Opening Balance | G105: INR Crs | J105: =IF(J104=1, $F102, I108) -> 0 | K105: =IF(K104=1, $F102, J108) -> 400 | L105: =IF(L104=1, $F102, K108) -> 400 | M105: =IF(M104=1, $F102, L108) -> 400 | N105: =IF(N104=1, $F102, M108) -> 400 | O105: =IF(O104=1, $F102, N108) -> 400
E106: Long Term Debt - Addition | G106: INR Crs
E107: Long Term Debt - Repayment | G107: INR Crs
E108: Long Term Debt - Closing Balance | G108: INR Crs | J108: =J105 + J106 - J107 -> 0 | K108: =K105 + K106 - K107 -> 400 | L108: =L105 + L106 - L107 -> 400 | M108: =M105 + M106 - M107 -> 400 | N108: =N105 + N106 - N107 -> 400 | O108: =O105 + O106 - O107 -> 400
E110: =E$30 -> Projections Active | F110: =F$30 -> 0 | G110: =G$30 -> Flag | H110: =H$30 -> 5 | I110: =I$30 -> 0 | J110: =J$30 -> 0 | K110: =K$30 -> 1 | L110: =L$30 -> 1 | ... O110: =O$30 -> 1
E111: Interest Expense | G111: INR Crs | J111: =IF(J110=1,$F101*SUM(J105:J106), 0) -> 0 | K111: =IF(K110=1,$F101*SUM(K105:K106), 0) -> 44 | L111: =IF(L110=1,$F101*SUM(L105:L106), 0) -> 44 | M111: =IF(M110=1,$F101*SUM(M105:M106), 0) -> 44 | N111: =IF(N110=1,$F101*SUM(N105:N106), 0) -> 44 | O111: =IF(O110=1,$F101*SUM(O105:O106), 0) -> 44
C113: Corporate Income Tax Rate
E114: =InpC!E$48 -> Corporate Tax Rate | F114: =InpC!F$48 -> 0.25 | G114: =InpC!G$48 -> %
E115: =E$30 -> Projections Active | F115: =F$30 -> 0 | G115: =G$30 -> Flag | H115: =H$30 -> 5 | I115: =I$30 -> 0 | J115: =J$30 -> 0 | K115: =K$30 -> 1 | L115: =L$30 -> 1 | ... O115: =O$30 -> 1
E116: =E$44 -> Profit Before Tax | F116: =F$44 -> 0 | G116: =G$44 -> INR Crs | H116: =H$44 -> 0 | I116: =I$44 -> 0 | J116: =J$44 -> 276 | K116: =K$44 -> 272.8 | L116: =L$44 -> 319 | ... O116: =O$44 -> 439.153
E117: Tax Expense | G117: INR Crs | J117: =IF(J115=1, $F114 * J$116, 0) -> 0 | K117: =IF(K115=1, $F114 * K$116, 0) -> 68.2 | L117: =IF(L115=1, $F114 * L$116, 0) -> 79.75 | M117: =IF(M115=1, $F114 * M$116, 0) -> 88.825 | N117: =IF(N115=1, $F114 * N$116, 0) -> 98.8075 | O117: =IF(O115=1, $F114 * O$116, 0) -> 109.78825
C119: Fixed Assets
E120: =InpC!E$49 -> Capital Expenditure | F120: =InpC!F$49 -> 0.1 | G120: =InpC!G$49 -> % of Revenue
E121: =InpC!E$54 -> Fixed Assets | F121: =InpC!F$54 -> 950 | G121: =InpC!G$54 -> INR Crs
E122: =E$30 -> Projections Active | F122: =F$30 -> 0 | G122: =G$30 -> Flag | H122: =H$30 -> 5 | I122: =I$30 -> 0 | J122: =J$30 -> 0 | K122: =K$30 -> 1 | L122: =L$30 -> 1 | ... O122: =O$30 -> 1
E123: =E$87 -> Revenue | F123: =F$87 -> 0 | G123: =G$87 -> INR Crs | H123: =H$87 -> 0 | I123: =I$87 -> 0 | J123: =J$87 -> 1200 | K123: =K$87 -> 1320 | L123: =L$87 -> 1452 | ... O123: =O$87 -> 1932.612
E125: =E$28 -> Projections Start | F125: =F$28 -> 0 | G125: =G$28 -> Flag | H125: =H$28 -> 1 | I125: =I$28 -> 0 | J125: =J$28 -> 0 | K125: =K$28 -> 1 | L125: =L$28 -> 0 | ... O125: =O$28 -> 0
E126: Fixed Assets - Opening Balance | G126: INR Crs | J126: =IF(J125=1, $F121, I129) -> 0 | K126: =IF(K125=1, $F121, J129) -> 950 | L126: =IF(L125=1, $F121, K129) -> 1016 | M126: =IF(M125=1, $F121, L129) -> 1088.6 | N126: =IF(N125=1, $F121, M129) -> 1168.46 | O126: =IF(O125=1, $F121, N129) -> 1256.306
E127: Fixed Assets - Capital Expenditure | G127: INR Crs | J127: =IF(J122=1, $F120 * J$123, 0) -> 0 | K127: =IF(K122=1, $F120 * K$123, 0) -> 132 | L127: =IF(L122=1, $F120 * L$123, 0) -> 145.2 | M127: =IF(M122=1, $F120 * M$123, 0) -> 159.72 | N127: =IF(N122=1, $F120 * N$123, 0) -> 175.692 | O127: =IF(O122=1, $F120 * O$123, 0) -> 193.2612
E128: Fixed Assets - Depreciation | G128: INR Crs | K128: =K$98 -> 66 | L128: =L$98 -> 72.6 | M128: =M$98 -> 79.86 | N128: =N$98 -> 87.846 | O128: =O$98 -> 96.6306
E129: Fixed Assets - Closing Balance | G129: INR Crs | J129: =J126 +J127 -J128 -> 0 | K129: =K126 +K127 -K128 -> 1016 | L129: =L126 +L127 -L128 -> 1088.6 | M129: =M126 +M127 -M128 -> 1168.46 | N129: =N126 +N127 -N128 -> 1256.306 | O129: =O126 +O127 -O128 -> 1352.9366
...

Sheet Transaction_Workings
E1: =Beta!E$13 -> Period Start | F1: =Beta!F$13 -> 0 | G1: =Beta!G$13 -> Date | H1: =Beta!H$13 -> 0 | I1: =Beta!I$13 -> 0 | J1: =Beta!J$13 -> 45658 | K1: =Beta!K$13 -> 46023 | L1: =Beta!L$13 -> 46388 | ... O1: =Beta!O$13 -> 47484
E2: =Beta!E$14 -> Period End | F2: =Beta!F$14 -> 0 | G2: =Beta!G$14 -> Date | H2: =Beta!H$14 -> 0 | I2: =Beta!I$14 -> 0 | J2: =Beta!J$14 -> 46022 | K2: =Beta!K$14 -> 46387 | L2: =Beta!L$14 -> 46752 | ... O2: =Beta!O$14 -> 47848
E3: =Beta!E$15 -> Number of Days | F3: =Beta!F$15 -> 0 | G3: =Beta!G$15 -> Days | H3: =Beta!H$15 -> 0 | I3: =Beta!I$15 -> 0 | J3: =Beta!J$15 -> 365 | K3: =Beta!K$15 -> 365 | L3: =Beta!L$15 -> 365 | ... O3: =Beta!O$15 -> 365
E4: =Beta!E$16 -> Financial Year | F4: =Beta!F$16 -> 0 | G4: =Beta!G$16 -> Year | H4: =Beta!H$16 -> 0 | I4: =Beta!I$16 -> 0 | J4: =Beta!J$16 -> 2025 | K4: =Beta!K$16 -> 2026 | L4: =Beta!L$16 -> 2027 | ... O4: =Beta!O$16 -> 2030
F6: Constant | G6: Unit | H6: Total
A7: VALUATION
E9: =InpC!E$48 -> Corporate Tax Rate | F9: =InpC!F$48 -> 0.25 | G9: =InpC!G$48 -> %
E10: =InpC!E$50 -> WACC | F10: =InpC!F$50 -> 0.12 | G10: =InpC!G$50 -> %
E11: =InpC!E$51 -> Terminal Growth Rate | F11: =InpC!F$51 -> 0.04 | G11: =InpC!G$51 -> %
E12: =Beta!E$30 -> Projections Active | F12: =Beta!F$30 -> 0 | G12: =Beta!G$30 -> Flag | H12: =Beta!H$30 -> 5 | I12: =Beta!I$30 -> 0 | J12: =Beta!J$30 -> 0 | K12: =Beta!K$30 -> 1 | L12: =Beta!L$30 -> 1 | ... O12: =Beta!O$30 -> 1
E13: =Beta!E$29 -> Projections End | F13: =Beta!F$29 -> 0 | G13: =Beta!G$29 -> Flag | H13: =Beta!H$29 -> 1 | I13: =Beta!I$29 -> 0 | J13: =Beta!J$29 -> 0 | K13: =Beta!K$29 -> 0 | L13: =Beta!L$29 -> 0 | ... O13: =Beta!O$29 -> 1
E14: =Beta!E$31 -> Projections Period | F14: =Beta!F$31 -> 0 | G14: =Beta!G$31 -> Year | H14: =Beta!H$31 -> 0 | I14: =Beta!I$31 -> 0 | J14: =Beta!J$31 -> 0 | K14: =Beta!K$31 -> 1 | L14: =Beta!L$31 -> 2 | ... O14: =Beta!O$31 -> 5
E15: =Beta!E$41 -> EBIT | F15: =Beta!F$41 -> 0 | G15: =Beta!G$41 -> INR Crs | H15: =Beta!H$41 -> 0 | I15: =Beta!I$41 -> 0 | J15: =Beta!J$41 -> 276 | K15: =Beta!K$41 -> 316.8 | L15: =Beta!L$41 -> 363 | ... O15: =Beta!O$41 -> 483.153
E16: Taxes | G16: INR Crs | J16: =IF(J12=1, $F9 * J$15, 0) -> 0 | K16: =IF(K12=1, $F9 * K$15, 0) -> 79.2 | L16: =IF(L12=1, $F9 * L$15, 0) -> 90.75 | M16: =IF(M12=1, $F9 * M$15, 0) -> 99.825 | N16: =IF(N12=1, $F9 * N$15, 0) -> 109.8075 | O16: =IF(O12=1, $F9 * O$15, 0) -> 120.78825
E17: NOPAT | G17: INR Crs | J17: =IF(J12=1, J15-J16, 0) -> 0 | K17: =IF(K12=1, K15-K16, 0) -> 237.6 | L17: =IF(L12=1, L15-L16, 0) -> 272.25 | M17: =IF(M12=1, M15-M16, 0) -> 299.475 | N17: =IF(N12=1, N15-N16, 0) -> 329.4225 | O17: =IF(O12=1, O15-O16, 0) -> 362.36475
E18: =Beta!E$40 -> Depreciation | F18: =Beta!F$40 -> 0 | G18: =Beta!G$40 -> INR Crs | H18: =Beta!H$40 -> 0 | I18: =Beta!I$40 -> 0 | J18: =Beta!J$40 -> 60 | K18: =Beta!K$40 -> 66 | L18: =Beta!L$40 -> 72.6 | ... O18: =Beta!O$40 -> 96.6306
E19: =Beta!E$67 -> Changes in working capital | F19: =Beta!F$67 -> 0 | G19: =Beta!G$67 -> INR Crs | H19: =Beta!H$67 -> 0 | I19: =Beta!I$67 -> 0 | J19: =Beta!J$67 -> 0 | K19: =Beta!K$67 -> 0 | L19: =Beta!L$67 -> 0 | ... O19: =Beta!O$67 -> 0
E20: =Beta!E$70 -> Capital Expenditure | F20: =Beta!F$70 -> 0 | G20: =Beta!G$70 -> INR Crs | H20: =Beta!H$70 -> 0 | I20: =Beta!I$70 -> 0 | J20: =Beta!J$70 -> 0 | K20: =Beta!K$70 -> -132 | L20: =Beta!L$70 -> -145.2 | ... O20: =Beta!O$70 -> -193.2612
E21: Free Cash Flow to Firm/ Unlevered Cash Flows | G21: INR Crs | J21: =IF(J12=1,SUM(J17:J20), 0) -> 0 | K21: =IF(K12=1,SUM(K17:K20), 0) -> 171.6 | L21: =IF(L12=1,SUM(L17:L20), 0) -> 199.65 | M21: =IF(M12=1,SUM(M17:M20), 0) -> 219.615 | N21: =IF(N12=1,SUM(N17:N20), 0) -> 241.5765 | O21: =IF(O12=1,SUM(O17:O20), 0) -> 265.73415
E22: Terminal Value of FCFF | G22: INR Crs | J22: =IF(J13=1, (J21*(1+$F$11))/($F$10-$F$11), 0) -> 0 | K22: =IF(K13=1, (K21*(1+$F$11))/($F$10-$F$11), 0) -> 0 | L22: =IF(L13=1, (L21*(1+$F$11))/($F$10-$F$11), 0) -> 0 | M22: =IF(M13=1, (M21*(1+$F$11))/($F$10-$F$11), 0) -> 0 | N22: =IF(N13=1, (N21*(1+$F$11))/($F$10-$F$11), 0) -> 0 | O22: =IF(O13=1, (O21*(1+$F$11))/($F$10-$F$11), 0) -> 3454.544
E23: Total Cashflows to be discounted | G23: INR Crs | J23: =SUM(J21:J22) -> 0 | K23: =SUM(K21:K22) -> 171.6 | L23: =SUM(L21:L22) -> 199.65 | M23: =SUM(M21:M22) -> 219.615 | N23: =SUM(N21:N22) -> 241.5765 | O23: =SUM(O21:O22) -> 3720.2781
E24: Discounting Factor | G24: % | J24: =IF(J12=1, 1/(1+$F$10)^J14, 0) -> 0 | K24: =IF(K12=1, 1/(1+$F$10)^K14, 0) -> 0.89285714 | L24: =IF(L12=1, 1/(1+$F$10)^L14, 0) -> 0.79719388 | M24: =IF(M12=1, 1/(1+$F$10)^M14, 0) -> 0.71178025 | N24: =IF(N12=1, 1/(1+$F$10)^N14, 0) -> 0.63551808 | O24: =IF(O12=1, 1/(1+$F$10)^O14, 0) -> 0.56742686
E25: Discounted Cash Flows | G25: INR Crs | J25: =J23 * J24 -> 0 | K25: =K23 * K24 -> 153.21429 | L25: =L23 * L24 -> 159.15976 | M25: =M23 * M24 -> 156.31762 | N25: =N23 * N24 -> 153.52623 | O25: =O23 * O24 -> 2110.9857
E27: Enterprise Value of Beta Componenets | F27: =SUM(J25:O25) -> 2733.2036 | G27: INR Crs
E28: =InpC!E$56 -> Cash | F28: =InpC!F$56 -> 120 | G28: =InpC!G$56 -> INR Crs
E29: =InpC!E$60 -> Long-term Debt | F29: =InpC!F$60 -> 400 | G29: =InpC!G$60 -> INR Crs
E30: Equity Value of Beta Components | F30: =F27 +F28 - F29 -> 2453.2036 | G30: INR Crs
A32: RATIOS
C34: Enterprise Value to EBITDA
E35: =E$27 -> Enterprise Value of Beta Componenets | F35: =F$27 -> 2733.2036 | G35: =G$27 -> INR Crs
E36: EBITDA | F36: =Beta!J$38 -> 336 | G36: INR Crs
E37: EV/ EBITDA | F37: =F35 / F36 -> 8.1345345 | G37: Times
C39: Price to Earnings Ratio
E40: =E$30 -> Equity Value of Beta Components | F40: =F$30 -> 2453.2036 | G40: =G$30 -> INR Crs
E41: Profit Ater Tax | F41: =Beta!J$47 -> 180 | G41: INR Crs
E42: P/E Ratio | F42: =F40 / F41 -> 13.628909 | G42: Times
A44: TRANSACTION DETAILS
E46: =InpC!E$66 -> Transaction Date | F46: =InpC!F$66 -> 46023 | G46: =InpC!G$66 -> Date
E47: =InpC!E$67 -> Transaction Premium | F47: =InpC!F$67 -> 0.25 | G47: =InpC!G$67 -> %
E48: =E$30 -> Equity Value of Beta Components | F48: =F$30 -> 2453.2036 | G48: =G$30 -> INR Crs
E49: Equity Value To be Paid | F49: =F48 *(1+F47) -> 3066.5045 | G49: INR Crs
E51: =InpC!E$68 -> Target Acquisition Proportion | F51: =InpC!F$68 -> 1 | G51: =InpC!G$68 -> %
E52: =E$49 -> Equity Value To be Paid | F52: =F$49 -> 3066.5045 | G52: =G$49 -> INR Crs
E53: Total Consideration to be Paid to Seller | F53: =F51 * F52 -> 3066.5045 | G53: INR Crs
B55: Deal Structure
E56: =InpC!E$71 -> Cash | F56: =InpC!F$71 -> 0.8 | G56: =InpC!G$71 -> %
E57: =InpC!E$72 -> Stock | F57: =InpC!F$72 -> 0.2 | G57: =InpC!G$72 -> %
E59: To be Paid in Cash | F59: =F$53 * F56 -> 2453.2036 | G59: INR Crs
E60: To be Paid in Stock | F60: =F$53 * F57 -> 613.3009 | G60: INR Crs
E61: Total Consideration to be paid to Seller | F61: =SUM(F59:F60) -> 3066.5045 | G61: INR Crs
E63: =InpC!E$74 -> Debt Raised in Lieu of Cash | F63: =InpC!F$74 -> 1 | G63: =InpC!G$74 -> %
E64: Total Debt Raised | F64: =F59 * F63 -> 2453.2036 | G64: INR Crs
E66: =E$60 -> To be Paid in Stock | F66: =F$60 -> 613.3009 | G66: =G$60 -> INR Crs
E67: =InpC!E$76 -> Alpha Ltd. Share Price | F67: =InpC!F$76 -> 65 | G67: =InpC!G$76 -> INR
E68: New Shares to be issued | F68: =F66 / F67 -> 9.4353985 | G68: Crores
B70: Transaction Fees
E71: =InpC!E$78 -> Transaction Expenses | F71: =InpC!F$78 -> 0.01 | G71: =InpC!G$78 -> % of Transaction Value
E72: =E$49 -> Equity Value To be Paid | F72: =F$49 -> 3066.5045 | G72: =G$49 -> INR Crs
E73: Total Transaction Fees | F73: =F71 * F72 -> 30.665045 | G73: INR Crs
B75: Balance Sheet Adjustments
J76: Alpha | K76: Beta | L76: Adjustments | M76: Proforma
E77: =InpC!E$33 -> Fixed Assets | J77: =InpC!F$33 -> 2500 | K77: =InpC!F$54 -> 950 | L77: =-F73 -> -30.665045 | M77: =SUM(J77:L77) -> 3419.335
E78: =InpC!E$34 -> Working Capital | J78: =InpC!F$34 -> 1300 | K78: =InpC!F$55 -> 480 | M78: =SUM(J78:L78) -> 1780
E79: =InpC!E$35 -> Cash | J79: =InpC!F$35 -> 400 | K79: =InpC!F$56 -> 120 | M79: =SUM(J79:L79) -> 520
E80: Goodwill | L80: =F72 - K83 -> 2366.5045 | M80: =SUM(J80:L80) -> 2366.5045
E81: =InpC!E$36 -> Total Assets | J81: =InpC!F$36 -> 4200 | K81: =InpC!F$57 -> 1550 | M81: =SUM(M77:M80) -> 8085.8395
E83: =InpC!E$38 -> Equity (Net Worth) | J83: =InpC!F$38 -> 2200 | K83: =InpC!F$59 -> 700 | L83: =-K83 + F66 -F73 -> -117.36414 | M83: =SUM(J83:L83) -> 2782.6359
E84: =InpC!E$39 -> Long-term Debt | J84: =InpC!F$39 -> 1000 | K84: =InpC!F$60 -> 400 | L84: =F64 -> 2453.2036 | M84: =SUM(J84:L84) -> 3853.2036
E85: =InpC!E$40 -> Other Liabilities | J85: =InpC!F$40 -> 1000 | K85: =InpC!F$61 -> 450 | M85: =SUM(J85:L85) -> 1450
E86: =InpC!E$41 -> Total Liabilities | J86: =InpC!F$41 -> 4200 | K86: =InpC!F$62 -> 1550 | M86: =SUM(M83:M85) -> 8085.8395
E88: Balance Sheet - Check | J88: =ROUND(J81 - J86, 2) -> 0 | K88: =ROUND(K81 - K86, 2) -> 0 | M88: =ROUND(M81 - M86, 2) -> 0

Sheet Post_Merger
E1: =Alpha!E$13 -> Period Start | F1: =Alpha!F$13 -> 0 | G1: =Alpha!G$13 -> Date | H1: =Alpha!H$13 -> 0 | I1: =Alpha!I$13 -> 0 | J1: =Alpha!J$13 -> 45658 | K1: =Alpha!K$13 -> 46023 | L1: =Alpha!L$13 -> 46388 | ... O1: =Alpha!O$13 -> 47484
E2: =Alpha!E$14 -> Period End | F2: =Alpha!F$14 -> 0 | G2: =Alpha!G$14 -> Date | H2: =Alpha!H$14 -> 0 | I2: =Alpha!I$14 -> 0 | J2: =Alpha!J$14 -> 46022 | K2: =Alpha!K$14 -> 46387 | L2: =Alpha!L$14 -> 46752 | ... O2: =Alpha!O$14 -> 47848
E3: =Alpha!E$15 -> Number of Days | F3: =Alpha!F$15 -> 0 | G3: =Alpha!G$15 -> Days | H3: =Alpha!H$15 -> 0 | I3: =Alpha!I$15 -> 0 | J3: =Alpha!J$15 -> 365 | K3: =Alpha!K$15 -> 365 | L3: =Alpha!L$15 -> 365 | ... O3: =Alpha!O$15 -> 365
E4: =Alpha!E$16 -> Financial Year | F4: =Alpha!F$16 -> 0 | G4: =Alpha!G$16 -> Year | H4: =Alpha!H$16 -> 0 | I4: =Alpha!I$16 -> 0 | J4: =Alpha!J$16 -> 2025 | K4: =Alpha!K$16 -> 2026 | L4: =Alpha!L$16 -> 2027 | ... O4: =Alpha!O$16 -> 2030
F6: Constant | G6: Unit | H6: Total
A7: FINANCIAL STATEMENTS
B9: Income Statement
E10: =E$75 -> Total Revenue | F10: =F$75 -> 0 | G10: =G$75 -> INR Crs | H10: =H$75 -> 0 | I10: =I$75 -> 0 | J10: =J$75 -> 6200 | K10: =K$75 -> 6720 | L10: =L$75 -> 7284 | ... O10: =O$75 -> 9279.2524
E11: =E$86 -> Total Operational Expenditure Post- Synergies | F11: =F$86 -> 0 | G11: =G$86 -> INR Crs | H11: =H$86 -> 0 | I11: =I$86 -> 0 | J11: =J$86 -> 4764 | K11: =K$86 -> 5249.2 | L11: =L$86 -> 5485.36 | ... O11: =O$86 -> 7003.2079
E12: EBITDA | F12: 0 | G12: INR Crs | J12: =J10 - J11 -> 1436 | K12: =K10 - K11 -> 1470.8 | L12: =L10 - L11 -> 1798.64 | M12: =M10 - M11 -> 1944.8432 | N12: =N10 - N11 -> 2103.6139 | O12: =O10 - O11 -> 2276.0445
E14: =E$91 -> Depreciation | F14: =F$91 -> 0 | G14: =G$91 -> INR Crs | H14: =H$91 -> 0 | I14: =I$91 -> 0 | J14: =J$91 -> 186 | K14: =K$91 -> 201.6 | L14: =L$91 -> 218.52 | ... O14: =O$91 -> 278.37757
E15: EBIT | G15: INR Crs | J15: =J12 - J14 -> 1250 | K15: =K12 - K14 -> 1269.2 | L15: =L12 - L14 -> 1580.12 | M15: =M12 - M14 -> 1707.9704 | N15: =N12 - N14 -> 1846.8329 | O15: =O12 - O14 -> 1997.6669
E17: =E$102 -> Interest Expense | F17: =F$102 -> 0 | G17: =G$102 -> INR Crs | H17: =H$102 -> 0 | I17: =I$102 -> 0 | J17: =J$102 -> 0 | K17: =K$102 -> 423.8524 | L17: =L$102 -> 423.8524 | ... O17: =O$102 -> 390.8524
E18: Profit Before Tax | G18: INR Crs | J18: =J15 - J17 -> 1250 | K18: =K15 - K17 -> 845.3476 | L18: =L15 - L17 -> 1156.2676 | M18: =M15 - M17 -> 1295.118 | N18: =N15 - N17 -> 1444.9805 | O18: =O15 - O17 -> 1606.8145
E20: =E$107 -> Corporate Income Tax | F20: =F$107 -> 0 | G20: =G$107 -> INR Crs | H20: =H$107 -> 0 | I20: =I$107 -> 0 | J20: =J$107 -> 312.5 | K20: =K$107 -> 211.3369 | L20: =L$107 -> 289.0669 | ... O20: =O$107 -> 401.70363
E21: Profit After Tax | G21: INR Crs | J21: =J18-J20 -> 937.5 | K21: =K18-K20 -> 634.0107 | L21: =L18-L20 -> 867.2007 | M21: =M18-M20 -> 971.3385 | N21: =N18-N20 -> 1083.7354 | O21: =O18-O20 -> 1205.1109
B23: Pre- Transaction
E24: =Alpha!E$48 -> Shares Outstanding | F24: =Alpha!F$48 -> 0 | G24: =Alpha!G$48 -> Crores | H24: =Alpha!H$48 -> 0 | I24: =Alpha!I$48 -> 0 | J24: =Alpha!J$48 -> 100 | K24: =Alpha!K$48 -> 100 | L24: =Alpha!L$48 -> 100 | ... O24: =Alpha!O$48 -> 100
E25: =Alpha!E$49 -> Earnings Per Share | F25: =Alpha!F$49 -> 0 | G25: =Alpha!G$49 -> INR | H25: =Alpha!H$49 -> 0 | I25: =Alpha!I$49 -> 0 | J25: =Alpha!J$49 -> 6.5 | K25: =Alpha!K$49 -> 6.945 | L25: =Alpha!L$49 -> 7.5606 | ... O25: =Alpha!O$49 -> 9.7189625
B27: Pre- Transaction
E28: =Transaction_Workings!E$68 -> New Shares to be issued | F28: =Transaction_Workings!F$68 -> 9.4353985 | G28: =Transaction_Workings!G$68 -> Crores
E29: Shares Outstanding | G29: Crores | J29: =J24 -> 100 | K29: =J29+$F$28 -> 109.4354 | L29: =K29 -> 109.4354 | M29: =L29 -> 109.4354 | N29: =M29 -> 109.4354 | O29: =N29 -> 109.4354
E30: Earnings Per Share | G30: INR | J30: =J21/ J29 -> 9.375 | K30: =K21/ K29 -> 5.79347 | L30: =L21/ L29 -> 7.9243162 | M30: =M21/ M29 -> 8.8759078 | N30: =N21/ N29 -> 9.9029693 | O30: =O21/ O29 -> 11.012076
E32: Accretion/ Dilution Analysis - INR | K32: =K30 - K25 -> -1.15153 | L32: =L30 - L25 -> 0.36371622 | M32: =M30 - M25 -> 0.65045977 | N32: =N30 - N25 -> 0.95948542 | O32: =O30 - O25 -> 1.2931131
E33: Accretion/ Dilution Analysis - % | K33: =K32/ K25 -> -0.16580705 | L33: =L32/ L25 -> 0.048106793 | M33: =M32/ M25 -> 0.079078947 | N33: =N32/ N25 -> 0.10728318 | O33: =O32/ O25 -> 0.13305053
B35: Balance Sheet
C36: Assets
E37: Fixed Assets | G37: INR Crs | J37: =Transaction_Workings!M$77 -> 3419.335 | K37: =J37- K14 -> 3217.735 | L37: =K37- L14 -> 2999.215 | M37: =L37- M14 -> 2762.3422 | N37: =M37- N14 -> 2505.5612 | O37: =N37- O14 -> 2227.1836
E38: Working Capital | G38: INR Crs | J38: =Transaction_Workings!M$78 -> 1780 | K38: =J38 -> 1780 | L38: =K38 -> 1780 | M38: =L38 -> 1780 | N38: =M38 -> 1780 | O38: =N38 -> 1780
E39: Cash | G39: INR Crs | J39: =Transaction_Workings!M$79 -> 520 | K39: =K65 -> 1355.6107 | L39: =L65 -> 2341.3314 | M39: =M65 -> 3449.5427 | N39: =N65 -> 4690.059 | O39: =O65 -> 6073.5475
E40: Goodwill | G40: INR Crs | J40: =Transaction_Workings!M$80 -> 2366.5045 | K40: =J40 -> 2366.5045 | L40: =K40 -> 2366.5045 | M40: =L40 -> 2366.5045 | N40: =M40 -> 2366.5045 | O40: =N40 -> 2366.5045
E41: Total Assets | G41: INR Crs | J41: =SUM(J37:J40) -> 8085.8395 | K41: =SUM(K37:K40) -> 8719.8502 | L41: =SUM(L37:L40) -> 9487.0509 | M41: =SUM(M37:M40) -> 10358.389 | N41: =SUM(N37:N40) -> 11342.125 | O41: =SUM(O37:O40) -> 12447.236
C43: Liabilities
E44: Equity (Net Worth) | G44: INR Crs | J44: =Transaction_Workings!M$83 -> 2782.6359 | K44: =J44 + K21 -> 3416.6466 | L44: =K44 + L21 -> 4283.8473 | M44: =L44 + M21 -> 5255.1858 | N44: =M44 + N21 -> 6338.9212 | O44: =N44 + O21 -> 7544.032
E45: Long-term Debt | G45: INR Crs | J45: =Transaction_Workings!M$84 -> 3853.2036 | K45: =K$100 -> 3853.2036 | L45: =L$100 -> 3753.2036 | M45: =M$100 -> 3653.2036 | N45: =N$100 -> 3553.2036 | O45: =O$100 -> 3453.2036
E46: Other Liabilities | G46: INR Crs | J46: =Transaction_Workings!M$85 -> 1450 | K46: =J46 -> 1450 | L46: =K46 -> 1450 | M46: =L46 -> 1450 | N46: =M46 -> 1450 | O46: =N46 -> 1450
E47: Total Liabilities | G47: INR Crs | J47: =SUM(J44:J46) -> 8085.8395 | K47: =SUM(K44:K46) -> 8719.8502 | L47: =SUM(L44:L46) -> 9487.0509 | M47: =SUM(M44:M46) -> 10358.389 | N47: =SUM(N44:N46) -> 11342.125 | O47: =SUM(O44:O46) -> 12447.236
E49: Balance sheet - Check | K49: =ROUND(J41 - J47, 2) -> 0 | L49: =ROUND(L41 - L47, 2) -> 0 | M49: =ROUND(M41 - M47, 2) -> 0 | N49: =ROUND(N41 - N47, 2) -> 0 | O49: =ROUND(O41 - O47, 2) -> 0
B51: Cash Flow Statement
E52: Profit After Tax | F52: 0 | G52: INR Crs | K52: =K21 -> 634.0107 | L52: =L21 -> 867.2007 | M52: =M21 -> 971.3385 | N52: =N21 -> 1083.7354 | O52: =O21 -> 1205.1109
E53: Depreciation | F53: 0 | G53: INR Crs | K53: =K14 -> 201.6 | L53: =L14 -> 218.52 | M53: =M14 -> 236.8728 | N53: =N14 -> 256.78094 | O53: =O14 -> 278.37757
E54: Changes in working capital | G54: INR Crs | L54: =J38-L38 -> 0 | M54: =L38-M38 -> 0 | N54: =M38-N38 -> 0 | O54: =N38-O38 -> 0
E55: Cash Flow From Operations | G55: INR Crs | K55: =SUM(K52:K54) -> 835.6107 | L55: =SUM(L52:L54) -> 1085.7207 | M55: =SUM(M52:M54) -> 1208.2113 | N55: =SUM(N52:N54) -> 1340.5163 | O55: =SUM(O52:O54) -> 1483.4885
E57: Capital Expenditure | G57: INR Crs
E58: Cash Flow From Investing Activities | G58: INR Crs | K58: =SUM(K57) -> 0 | L58: =SUM(L57) -> 0 | M58: =SUM(M57) -> 0 | N58: =SUM(N57) -> 0 | O58: =SUM(O57) -> 0
E60: Debt Repayment | L60: =-L99 -> -100 | M60: =-M99 -> -100 | N60: =-N99 -> -100 | O60: =-O99 -> -100
E61: Cash Flow From Financing Activities | G61: INR Crs | K61: =SUM(K60) -> 0 | L61: =SUM(L60) -> -100 | M61: =SUM(M60) -> -100 | N61: =SUM(N60) -> -100 | O61: =SUM(O60) -> -100
E63: Opening Cash | G63: INR Crs | K63: =J65 -> 520 | L63: =K65 -> 1355.6107 | M63: =L65 -> 2341.3314 | N63: =M65 -> 3449.5427 | O63: =N65 -> 4690.059
E64: Net Change in Cash | G64: INR Crs | K64: =K55 + K58 + K61 -> 835.6107 | L64: =L55 + L58 + L61 -> 985.7207 | M64: =M55 + M58 + M61 -> 1108.2113 | N64: =N55 + N58 + N61 -> 1240.5163 | O64: =O55 + O58 + O61 -> 1383.4885
E65: Closing Cash | G65: INR Crs | J65: =J39 -> 520 | K65: =SUM(K63:K64) -> 1355.6107 | L65: =SUM(L63:L64) -> 2341.3314 | M65: =SUM(M63:M64) -> 3449.5427 | N65: =SUM(N63:N64) -> 4690.059 | O65: =SUM(O63:O64) -> 6073.5475
A67: SCHEDULES
B69: Revenue
C70: Alpha
E71: =Alpha!E$89 -> Revenue | F71: =Alpha!F$89 -> 0 | G71: =Alpha!G$89 -> INR Crs | H71: =Alpha!H$89 -> 0 | I71: =Alpha!I$89 -> 0 | J71: =Alpha!J$89 -> 5000 | K71: =Alpha!K$89 -> 5400 | L71: =Alpha!L$89 -> 5832 | ... O71: =Alpha!O$89 -> 7346.6404
C73: Beta
E74: =Beta!E$87 -> Revenue | F74: =Beta!F$87 -> 0 | G74: =Beta!G$87 -> INR Crs | H74: =Beta!H$87 -> 0 | I74: =Beta!I$87 -> 0 | J74: =Beta!J$87 -> 1200 | K74: =Beta!K$87 -> 1320 | L74: =Beta!L$87 -> 1452 | ... O74: =Beta!O$87 -> 1932.612
E75: Total Revenue | G75: INR Crs | J75: =SUM(J71, J74) -> 6200 | K75: =SUM(K71, K74) -> 6720 | L75: =SUM(L71, L74) -> 7284 | M75: =SUM(M71, M74) -> 7895.76 | N75: =SUM(N71, N74) -> 8559.3648 | O75: =SUM(O71, O74) -> 9279.2524
B77: Operational Expenditure
C78: Alpha
E79: =Alpha!E$36 -> Operating Expenses | F79: =Alpha!F$36 -> 0 | G79: =Alpha!G$36 -> INR Crs | H79: =Alpha!H$36 -> 0 | I79: =Alpha!I$36 -> 0 | J79: =Alpha!J$36 -> 3900 | K79: =Alpha!K$36 -> 4212 | L79: =Alpha!L$36 -> 4548.96 | ... O79: =Alpha!O$36 -> 5730.3795
C81: Beta
E82: =Beta!E$37 -> Operating Expenses | F82: =Beta!F$37 -> 0 | G82: =Beta!G$37 -> INR Crs | H82: =Beta!H$37 -> 0 | I82: =Beta!I$37 -> 0 | J82: =Beta!J$37 -> 864 | K82: =Beta!K$37 -> 937.2 | L82: =Beta!L$37 -> 1016.4 | ... O82: =Beta!O$37 -> 1352.8284
E83: Total Operational Expenditure Pre- Synergies | G83: INR Crs | J83: =SUM(J79, J82) -> 4764 | K83: =SUM(K79, K82) -> 5149.2 | L83: =SUM(L79, L82) -> 5565.36 | M83: =SUM(M79, M82) -> 6030.9168 | N83: =SUM(N79, N82) -> 6535.7509 | O83: =SUM(O79, O82) -> 7083.2079
E84: =InpC!E$85 -> Integration Cost | F84: =InpC!F$85 -> 100 | G84: =InpC!G$85 -> INR Crs | K84: =F84 -> 100
E85: =InpC!E$83 -> Cost Synergies | F85: =InpC!F$83 -> 80 | G85: =InpC!G$83 -> INR Crs | L85: =-$F$85 -> -80 | M85: =-$F$85 -> -80 | N85: =-$F$85 -> -80 | O85: =-$F$85 -> -80
E86: Total Operational Expenditure Post- Synergies | G86: INR Crs | J86: =SUM(J83:J85) -> 4764 | K86: =SUM(K83:K85) -> 5249.2 | L86: =SUM(L83:L85) -> 5485.36 | M86: =SUM(M83:M85) -> 5950.9168 | N86: =SUM(N83:N85) -> 6455.7509 | O86: =SUM(O83:O85) -> 7003.2079
B88: Depreciation
E89: =InpC!E$26 -> Depreciation | F89: =InpC!F$26 -> 0.03 | G89: =InpC!G$26 -> % of Revenue
E90: =E$75 -> Total Revenue | F90: =F$75 -> 0 | G90: =G$75 -> INR Crs | H90: =H$75 -> 0 | I90: =I$75 -> 0 | J90: =J$75 -> 6200 | K90: =K$75 -> 6720 | L90: =L$75 -> 7284 | ... O90: =O$75 -> 9279.2524
E91: Depreciation | G91: INR Crs | J91: =$F89 * J$90 -> 186 | K91: =$F89 * K$90 -> 201.6 | L91: =$F89 * L$90 -> 218.52 | M91: =$F89 * M$90 -> 236.8728 | N91: =$F89 * N$90 -> 256.78094 | O91: =$F89 * O$90 -> 278.37757
B93: Debt
E94: =InpC!E$88 -> Interest Rate | F94: =InpC!F$88 -> 0.11 | G94: =InpC!G$88 -> %
E95: Long-term Debt | F95: =Transaction_Workings!M$84 -> 3853.2036 | G95: INR Crs
E97: Debt - Opening Balance | G97: INR Crs | J97: =I100 -> 0 | K97: =J100 -> 3853.2036 | L97: =K100 -> 3853.2036 | M97: =L100 -> 3753.2036 | N97: =M100 -> 3653.2036 | O97: =N100 -> 3553.2036
E98: Debt - Addition | G98: INR Crs
E99: Debt - Repayment | G99: INR Crs | K99: 0 | L99: 100 | M99: 100 | N99: 100 | O99: 100
E100: Debt - Closing Balance | G100: INR Crs | J100: =$F$95 -> 3853.2036 | K100: =K97 + K98 -K99 -> 3853.2036 | L100: =L97 + L98 -L99 -> 3753.2036 | M100: =M97 + M98 -M99 -> 3653.2036 | N100: =N97 + N98 -N99 -> 3553.2036 | O100: =O97 + O98 -O99 -> 3453.2036
E102: Interest Expense | G102: INR Crs | J102: =SUM(J97)*$F94 -> 0 | K102: =SUM(K97)*$F94 -> 423.8524 | L102: =SUM(L97)*$F94 -> 423.8524 | M102: =SUM(M97)*$F94 -> 412.8524 | N102: =SUM(N97)*$F94 -> 401.8524 | O102: =SUM(O97)*$F94 -> 390.8524
B104: Corporate Income Tax
E105: =InpC!E$28 -> Corporate Tax Rate | F105: =InpC!F$28 -> 0.25 | G105: =InpC!G$28 -> %
E106: =E$18 -> Profit Before Tax | F106: =F$18 -> 0 | G106: =G$18 -> INR Crs | H106: =H$18 -> 0 | I106: =I$18 -> 0 | J106: =J$18 -> 1250 | K106: =K$18 -> 845.3476 | L106: =L$18 -> 1156.2676 | ... O106: =O$18 -> 1606.8145
E107: Corporate Income Tax | G107: INR Crs | J107: =$F105 * J$106 -> 312.5 | K107: =$F105 * K$106 -> 211.3369 | L107: =$F105 * L$106 -> 289.0669 | M107: =$F105 * M$106 -> 323.7795 | N107: =$F105 * N$106 -> 361.24513 | O107: =$F105 * O$106 -> 401.70363
A109: ANALYSIS
B111: Interest Coverage Ratio
C112: Accrual Basis
E113: =E$12 -> EBITDA | F113: =F$12 -> 0 | G113: =G$12 -> INR Crs | H113: =H$12 -> 0 | I113: =I$12 -> 0 | J113: =J$12 -> 1436 | K113: =K$12 -> 1470.8 | L113: =L$12 -> 1798.64 | ... O113: =O$12 -> 2276.0445
E114: =E$17 -> Interest Expense | F114: =F$17 -> 0 | G114: =G$17 -> INR Crs | H114: =H$17 -> 0 | I114: =I$17 -> 0 | J114: =J$17 -> 0 | K114: =K$17 -> 423.8524 | L114: =L$17 -> 423.8524 | ... O114: =O$17 -> 390.8524
E115: Interest Service Coverage Ratio | G115: Times | K115: =K113 / K114 -> 3.4700759 | L115: =L113 / L114 -> 4.2435527 | M115: =M113 / M114 -> 4.710747 | N115: =N113 / N114 -> 5.2347924 | O115: =O113 / O114 -> 5.8232839
C117: Cash Basis
E118: =E$55 -> Cash Flow From Operations | F118: =F$55 -> 0 | G118: =G$55 -> INR Crs | H118: =H$55 -> 0 | I118: =I$55 -> 0 | J118: =J$55 -> 0 | K118: =K$55 -> 835.6107 | L118: =L$55 -> 1085.7207 | ... O118: =O$55 -> 1483.4885
E119: =E$17 -> Interest Expense | F119: =F$17 -> 0 | G119: =G$17 -> INR Crs | H119: =H$17 -> 0 | I119: =I$17 -> 0 | J119: =J$17 -> 0 | K119: =K$17 -> 423.8524 | L119: =L$17 -> 423.8524 | ... O119: =O$17 -> 390.8524
E120: =E$57 -> Capital Expenditure | F120: =F$57 -> 0 | G120: =G$57 -> INR Crs | H120: =H$57 -> 0 | I120: =I$57 -> 0 | J120: =J$57 -> 0 | K120: =K$57 -> 0 | L120: =L$57 -> 0 | ... O120: =O$57 -> 0
E121: Total Cash Available for Interest Payment | G121: Times | K121: =SUM(K118:K120) -> 1259.4631 | L121: =SUM(L118:L120) -> 1509.5731 | M121: =SUM(M118:M120) -> 1621.0637 | N121: =SUM(N118:N120) -> 1742.3687 | O121: =SUM(O118:O120) -> 1874.3409
E123: =E$17 -> Interest Expense | F123: =F$17 -> 0 | G123: =G$17 -> INR Crs | H123: =H$17 -> 0 | I123: =I$17 -> 0 | J123: =J$17 -> 0 | K123: =K$17 -> 423.8524 | L123: =L$17 -> 423.8524 | ... O123: =O$17 -> 390.8524
E124: Interest Service Coverage Ratio | G124: Times | K124: =K121 / K123 -> 2.9714663 | L124: =L121 / L123 -> 3.5615538 | M124: =M121 / M123 -> 3.926497 | N124: =N121 / N123 -> 4.3358426 | O124: =O121 / O123 -> 4.795521
B126: Debt Service Coverage Ratio
C127: Accrual Basis
E128: =E$12 -> EBITDA | F128: =F$12 -> 0 | G128: =G$12 -> INR Crs | H128: =H$12 -> 0 | I128: =I$12 -> 0 | J128: =J$12 -> 1436 | K128: =K$12 -> 1470.8 | L128: =L$12 -> 1798.64 | ... O128: =O$12 -> 2276.0445
E129: =E$17 -> Interest Expense | F129: =F$17 -> 0 | G129: =G$17 -> INR Crs | H129: =H$17 -> 0 | I129: =I$17 -> 0 | J129: =J$17 -> 0 | K129: =K$17 -> 423.8524 | L129: =L$17 -> 423.8524 | ... O129: =O$17 -> 390.8524
E130: =E$99 -> Debt - Repayment | F130: =F$99 -> 0 | G130: =G$99 -> INR Crs | H130: =H$99 -> 0 | I130: =I$99 -> 0 | J130: =J$99 -> 0 | K130: =K$99 -> 0 | L130: =L$99 -> 100 | ... O130: =O$99 -> 100
...

Sheet Temp
F6: Constant | G6: Unit | H6: Total
